setup.py
verysimplemodule_luan/__init__.py
verysimplemodule_luan/add.py
verysimplemodule_luan/sub.py
verysimplemodule_luan.egg-info/PKG-INFO
verysimplemodule_luan.egg-info/SOURCES.txt
verysimplemodule_luan.egg-info/dependency_links.txt
verysimplemodule_luan.egg-info/top_level.txt
verysimplemodule_luan/extra/__init__.py
verysimplemodule_luan/extra/div.py
verysimplemodule_luan/extra/mult.py